nfflr/__init__.py
nfflr/ase.py
nfflr/atoms.py
nfflr/distributed.py
nfflr/train.py
nfflr/train_ff.py
nfflr/training_utils.py
nfflr/data/__init__.py
nfflr/data/asedataset.py
nfflr/data/atoms.py
nfflr/data/dataset.py
nfflr/data/datasets.py
nfflr/data/graph.py
nfflr/data/test.py
nfflr/data/datasets/__init__.py
nfflr/data/datasets/alignn.py
nfflr/data/datasets/deepmd.py
nfflr/data/datasets/matpes.py
nfflr/data/datasets/mlearn.py
nfflr/data/datasets/vasp.py
nfflr/models/__init__.py
nfflr/models/abstract.py
nfflr/models/utils.py
nfflr/models/classical/__init__.py
nfflr/models/classical/eam.py
nfflr/models/classical/eam_check.py
nfflr/models/classical/embedded_atom.py
nfflr/models/classical/lj.py
nfflr/models/classical/smeam.py
nfflr/models/classical/tersoff.py
nfflr/models/gnn/__init__.py
nfflr/models/gnn/alignn.py
nfflr/models/gnn/alignn_ff.py
nfflr/models/gnn/alignn_ff_fcut.py
nfflr/models/gnn/alignn_reference.py
nfflr/models/gnn/bond_order.py
nfflr/models/gnn/equiformer.py
nfflr/models/gnn/gcn.py
nfflr/models/gnn/icgcnn.py
nfflr/models/gnn/modified_cgcnn.py
nfflr/models/gnn/nep.py
nfflr/models/gnn/schnet.py
nfflr/models/gnn/tfm.py
nfflr/models/gnn/transformer.py
nfflr/nn/__init__.py
nfflr/nn/cutoff.py
nfflr/nn/loss.py
nfflr/nn/transform.py
nfflr/nn/layers/__init__.py
nfflr/nn/layers/alignn.py
nfflr/nn/layers/atomfeatures.py
nfflr/nn/layers/basis.py
nfflr/nn/layers/common.py
nfflr/nn/layers/conv.py
nfflr/nn/layers/force.py
nfflr/nn/layers/norm.py
nfflr/train/__init__.py
nfflr/train/config.py
nfflr/train/distributed.py
nfflr/train/evaluation.py
nfflr/train/swag.py
nfflr/train/train_ff.py
nfflr/train/trainer.py
nfflr/train/utils.py
nfflr-0.4.1.dist-info/licenses/LICENSE.rst
nfflr-0.4.1.dist-info/METADATA
nfflr-0.4.1.dist-info/WHEEL
nfflr-0.4.1.dist-info/entry_points.txt
nfflr-0.4.1.dist-info/top_level.txt
nfflr-0.4.1.dist-info/RECORD
