Metadata-Version: 2.4
Name: nfflr
Version: 0.4.1
Summary: neural force field learning toolkit
Author-email: Brian DeCost <brian.decost@nist.gov>
Project-URL: homepage, https://pages.nist.gov/nfflr
Project-URL: documentation, https://pages.nist.gov/nfflr
Project-URL: repository, https://github.com/usnistgov/nfflr
Project-URL: issues, https://github.com/usnistgov/nfflr/issues
Requires-Python: <3.13,>=3.8
License-File: LICENSE.rst
Requires-Dist: ase
Requires-Dist: ray[tune]
Requires-Dist: numpy; sys_platform == "linux"
Requires-Dist: numpy<2.0.0; sys_platform == "darwin"
Requires-Dist: scipy
Requires-Dist: torch==2.4; sys_platform == "linux"
Requires-Dist: torch==2.1.0; sys_platform == "darwin"
Requires-Dist: torchdata==0.7.0; sys_platform == "darwin"
Requires-Dist: typer
Requires-Dist: einops
Requires-Dist: pandas
Requires-Dist: pynvml
Requires-Dist: pykeops
Requires-Dist: pynvml>=11.5.3
Requires-Dist: lmdb>=1.6.2
Requires-Dist: mendeleev
Requires-Dist: matplotlib
Requires-Dist: cached-path
Requires-Dist: platformdirs
Requires-Dist: plum-dispatch
Requires-Dist: pytorch-ignite
Requires-Dist: py-config-runner
Requires-Dist: dgl>=2.4.0; sys_platform == "linux"
Requires-Dist: dgl==2.1.0; sys_platform == "darwin"
Requires-Dist: jarvis-tools>=2021.07.19
Dynamic: license-file
